pyfigshare/__init__.py
pyfigshare/_version.py
pyfigshare/figshare.py
pyfigshare/figshare_v2.py
pyfigshare-0.6.dist-info/LICENSE
pyfigshare-0.6.dist-info/METADATA
pyfigshare-0.6.dist-info/WHEEL
pyfigshare-0.6.dist-info/entry_points.txt
pyfigshare-0.6.dist-info/top_level.txt
pyfigshare-0.6.dist-info/RECORD
