Metadata-Version: 2.2
Name: pyfigshare
Version: 0.6
Summary: A python package to interact with figshare
Home-page: https://github.com/DingWB/pyfigshare
Author: Wubin Ding
Author-email: Wubin Ding <ding.wu.bin.gm@gmail.com>
License: MIT License
Project-URL: Homepage, https://github.com/DingWB/pyfigshare
Project-URL: repository, https://github.com/DingWB/pyfigshare
Project-URL: Bug Tracker, https://github.com/DingWB/pyfigshare/issues
Project-URL: documentation, https://dingwb.github.io/pyfigshare
Keywords: pyfigshare,figshare
Classifier: Programming Language :: Python :: 3
Classifier: License :: OSI Approved :: MIT License
Classifier: Operating System :: OS Independent
Requires-Python: >=3.0
License-File: LICENSE
Requires-Dist: fire
Requires-Dist: pandas
Requires-Dist: requests
Requires-Dist: loguru
Dynamic: author
Dynamic: home-page
